tree_sitter_jinja/_binding.abi3.so
tree_sitter_jinja/__init__.py
tree_sitter_jinja/__init__.pyi
tree_sitter_jinja/py.typed
tree_sitter_jinja/binding.c
tree_sitter_jinja/queries/highlights.scm
tree_sitter_jinja/queries/injections.scm
tree_sitter_jinja3-0.11.0.dist-info/METADATA
tree_sitter_jinja3-0.11.0.dist-info/top_level.txt
tree_sitter_jinja3-0.11.0.dist-info/WHEEL
tree_sitter_jinja3-0.11.0.dist-info/RECORD
