Metadata-Version: 2.1
Name: tree-sitter-jinja3
Version: 0.11.0
Summary: Jinja grammar for tree-sitter
License: MIT
Project-URL: Homepage, https://github.com/tree-sitter/tree-sitter-jinja
Keywords: incremental,parsing,tree-sitter,jinja
Classifier: Intended Audience :: Developers
Classifier: License :: OSI Approved :: MIT License
Classifier: Topic :: Software Development :: Compilers
Classifier: Topic :: Text Processing :: Linguistic
Classifier: Typing :: Typed
Requires-Python: >=3.8
Provides-Extra: core
Requires-Dist: tree-sitter~=0.21; extra == "core"
